compassist/__init__.py
compassist/compassist.py
compassist-0.3.1.dist-info/METADATA
compassist-0.3.1.dist-info/WHEEL
compassist-0.3.1.dist-info/LICENSE
compassist-0.3.1.dist-info/RECORD
