Metadata-Version: 2.1
Name: compassist
Version: 0.3.1
Summary: A set of tools to help commpute task time/ probabilies for video game completionist tasks
Home-page: https://github.com/UBC-MDS/compassist
License: MIT
Author: Samson Bakos, Waiel Tinwala, Marian Agyby and Ashwin Babu
Requires-Python: >=3.9,<3.12
Classifier: License :: OSI Approved :: MIT License
Classifier: Programming Language :: Python :: 3
Classifier: Programming Language :: Python :: 3.9
Classifier: Programming Language :: Python :: 3.10
Classifier: Programming Language :: Python :: 3.11
Requires-Dist: matplotlib (>=3.6.3)
Requires-Dist: numpy (>=1.24.1,<2.0.0)
Requires-Dist: python-semantic-release (>=7.33.0,<8.0.0)
Project-URL: Documentation, https://compassist.readthedocs.io
Project-URL: Repository, https://github.com/UBC-MDS/compassist
